LICENSE
drf_react_template/__init__.py
drf_react_template/mixins.py
drf_react_template/renderers.py
drf_react_template/schema_form_encoder.py
drf_react_template_framework-0.0.17.dist-info/LICENSE
drf_react_template_framework-0.0.17.dist-info/WHEEL
drf_react_template_framework-0.0.17.dist-info/METADATA
drf_react_template_framework-0.0.17.dist-info/RECORD
