Metadata-Version: 2.1
Name: drf-react-template-framework
Version: 0.0.17
Summary: Django REST Framework plugin that creates form schemas for react-jsonschema-form
Home-page: https://github.com/yoyowallet/drf-react-template-framework
License: MIT
Keywords: drf,react
Author: stuart.bradley
Author-email: stuy.bradley@gmail.com
Requires-Python: >=3.7,<4.0
Classifier: Development Status :: 3 - Alpha
Classifier: Framework :: Django
Classifier: Intended Audience :: Developers
Classifier: License :: OSI Approved :: MIT License
Classifier: Operating System :: OS Independent
Classifier: Programming Language :: Python :: 3
Classifier: Programming Language :: Python :: 3.10
Classifier: Programming Language :: Python :: 3.7
Classifier: Programming Language :: Python :: 3.8
Classifier: Programming Language :: Python :: 3.9
Classifier: Topic :: Software Development :: Libraries
Requires-Dist: djangorestframework (>=3.12.0,<4.0.0)
Project-URL: Repository, https://github.com/yoyowallet/drf-react-template-framework
